ryp.py
ryp-0.2.0.dist-info/licenses/LICENSE
ryp-0.2.0.dist-info/METADATA
ryp-0.2.0.dist-info/WHEEL
ryp-0.2.0.dist-info/top_level.txt
ryp-0.2.0.dist-info/RECORD
