Metadata-Version: 2.4
Name: ryp
Version: 0.2.0
Summary: R inside Python
Author-email: Michael Wainberg <m.wainberg@utoronto.ca>
License-Expression: MIT
Project-URL: Homepage, https://github.com/Wainberg/ryp
Project-URL: Bug Tracker, https://github.com/Wainberg/ryp/issues
Keywords: R,rpy2,reticulate,tidyverse,ggplot,ggplot2,arrow
Classifier: Intended Audience :: Developers
Classifier: Intended Audience :: Science/Research
Classifier: Operating System :: OS Independent
Classifier: Programming Language :: Python :: 3
Classifier: Programming Language :: Python :: 3.7
Classifier: Programming Language :: Python :: 3.8
Classifier: Programming Language :: Python :: 3.9
Classifier: Programming Language :: Python :: 3.10
Classifier: Programming Language :: Python :: 3.11
Classifier: Programming Language :: Python :: 3.12
Classifier: Programming Language :: Python :: 3.13
Classifier: Topic :: Scientific/Engineering
Classifier: Topic :: Software Development
Requires-Python: >=3.8
License-File: LICENSE
Requires-Dist: cffi
Requires-Dist: pyarrow
Dynamic: license-file
